pyabc/__init__.py
pyabc/platform_factory.py
pyabc/version.py
pyabc/acceptor/__init__.py
pyabc/acceptor/acceptor.py
pyabc/acceptor/pdf_norm.py
pyabc/copasi/__init__.py
pyabc/copasi/model.py
pyabc/cv/__init__.py
pyabc/cv/bootstrap.py
pyabc/cv/powerlaw.py
pyabc/distance/__init__.py
pyabc/distance/aggregate.py
pyabc/distance/base.py
pyabc/distance/distance.py
pyabc/distance/kernel.py
pyabc/distance/ot.py
pyabc/distance/pnorm.py
pyabc/distance/scale.py
pyabc/distance/util.py
pyabc/epsilon/__init__.py
pyabc/epsilon/base.py
pyabc/epsilon/epsilon.py
pyabc/epsilon/silk.py
pyabc/epsilon/temperature.py
pyabc/external/__init__.py
pyabc/external/base.py
pyabc/external/utils.py
pyabc/external/julia/__init__.py
pyabc/external/julia/jl_pyjulia.py
pyabc/external/r/__init__.py
pyabc/external/r/r_rpy2.py
pyabc/inference/__init__.py
pyabc/inference/smc.py
pyabc/inference_util/__init__.py
pyabc/inference_util/inference_util.py
pyabc/model/__init__.py
pyabc/model/model.py
pyabc/parameters/__init__.py
pyabc/parameters/parameters.py
pyabc/petab/__init__.py
pyabc/petab/amici.py
pyabc/petab/base.py
pyabc/population/__init__.py
pyabc/population/population.py
pyabc/populationstrategy/__init__.py
pyabc/populationstrategy/populationstrategy.py
pyabc/predictor/__init__.py
pyabc/predictor/predictor.py
pyabc/random_choice/__init__.py
pyabc/random_choice/random_choice.py
pyabc/random_variables/__init__.py
pyabc/random_variables/random_variables.py
pyabc/sampler/__init__.py
pyabc/sampler/base.py
pyabc/sampler/concurrent_future.py
pyabc/sampler/dask_sampler.py
pyabc/sampler/eps_mixin.py
pyabc/sampler/mapping.py
pyabc/sampler/multicore.py
pyabc/sampler/multicore_evaluation_parallel.py
pyabc/sampler/multicorebase.py
pyabc/sampler/singlecore.py
pyabc/sampler/util.py
pyabc/sampler/redis_eps/__init__.py
pyabc/sampler/redis_eps/cli.py
pyabc/sampler/redis_eps/cmd.py
pyabc/sampler/redis_eps/redis_logging.py
pyabc/sampler/redis_eps/sampler.py
pyabc/sampler/redis_eps/sampler_static.py
pyabc-0.12.16.dist-info/licenses/LICENSE.txt
pyabc-0.12.16.dist-info/METADATA
pyabc-0.12.16.dist-info/WHEEL
pyabc-0.12.16.dist-info/entry_points.txt
pyabc-0.12.16.dist-info/top_level.txt
pyabc-0.12.16.dist-info/RECORD
