Metadata-Version: 2.4
Name: pyabc
Version: 0.12.16
Summary: Distributed, likelihood-free ABC-SMC inference
Home-page: https://github.com/icb-dcm/pyabc
Download-URL: https://github.com/icb-dcm/pyabc/releases
Author: The pyABC developers
Author-email: yannik.schaelte@gmail.com
Maintainer: Yannik Schaelte
Maintainer-email: yannik.schaelte@gmail.com
License: BSD-3-Clause
Project-URL: Bug Tracker, https://github.com/icb-dcm/pyabc/issues
Project-URL: Documentation, https://pyabc.readthedocs.io
Project-URL: Changelog, https://github.com/ICB-DCM/pyABC/blob/main/CHANGELOG.rst
Keywords: likelihood-free,inference,abc,approximate bayesian computation,sge,distributed
Classifier: Development Status :: 5 - Production/Stable
Classifier: License :: OSI Approved :: BSD License
Classifier: Operating System :: OS Independent
Classifier: Programming Language :: Python
Classifier: Programming Language :: Python :: 3.12
Classifier: Programming Language :: Python :: 3.11
Classifier: Programming Language :: Python :: 3.10
Requires-Python: >=3.10
License-File: LICENSE.txt
Requires-Dist: numpy>=1.23.5
Requires-Dist: scipy>=1.5.2
Requires-Dist: pandas>=2.0.1
Requires-Dist: cloudpickle>=1.5.0
Requires-Dist: scikit-learn>=0.23.1
Requires-Dist: click>=7.1.2
Requires-Dist: redis>=2.10.6
Requires-Dist: distributed>=2022.10.2
Requires-Dist: matplotlib>=3.3.0
Requires-Dist: sqlalchemy
Requires-Dist: jabbar>=0.0.10
Requires-Dist: gitpython>=3.1.7
Provides-Extra: webserver-flask
Requires-Dist: flask-bootstrap>=3.3.7.1; extra == "webserver-flask"
Requires-Dist: flask>=1.1.2; extra == "webserver-flask"
Requires-Dist: bokeh>=3.0.1; extra == "webserver-flask"
Provides-Extra: webserver-dash
Requires-Dist: dash>=2.11.1; extra == "webserver-dash"
Requires-Dist: dash-bootstrap-components>=1.4.2; extra == "webserver-dash"
Provides-Extra: pyarrow
Requires-Dist: pyarrow>=6.0.0; extra == "pyarrow"
Provides-Extra: r
Requires-Dist: rpy2>=3.4.4; extra == "r"
Requires-Dist: cffi>=1.14.5; extra == "r"
Requires-Dist: ipython>=7.18.1; extra == "r"
Requires-Dist: pygments>=2.6.1; extra == "r"
Provides-Extra: julia
Requires-Dist: julia>=0.5.7; extra == "julia"
Requires-Dist: pygments>=2.6.1; extra == "julia"
Provides-Extra: copasi
Requires-Dist: copasi-basico>=0.8; extra == "copasi"
Provides-Extra: ot
Requires-Dist: pot>=0.7.0; extra == "ot"
Provides-Extra: petab
Requires-Dist: petab>=0.2.0; extra == "petab"
Provides-Extra: amici
Requires-Dist: amici>=0.18.0; extra == "amici"
Provides-Extra: yaml2sbml
Requires-Dist: yaml2sbml>=0.2.1; extra == "yaml2sbml"
Provides-Extra: migrate
Requires-Dist: alembic>=1.5.4; extra == "migrate"
Provides-Extra: plotly
Requires-Dist: plotly>=5.3.1; extra == "plotly"
Requires-Dist: kaleido>=0.2.1; extra == "plotly"
Provides-Extra: autograd
Requires-Dist: autograd>=1.3; extra == "autograd"
Provides-Extra: examples
Requires-Dist: notebook>=6.1.4; extra == "examples"
Provides-Extra: doc
Requires-Dist: sphinx>=8.1.3; extra == "doc"
Requires-Dist: nbsphinx>=0.9.5; extra == "doc"
Requires-Dist: nbconvert>=7.16.4; extra == "doc"
Requires-Dist: sphinx-rtd-theme>=1.2.0; extra == "doc"
Requires-Dist: sphinx-autodoc-typehints>=1.18.3; extra == "doc"
Requires-Dist: ipython>=8.4.0; extra == "doc"
Provides-Extra: test
Requires-Dist: pytest>=5.4.3; extra == "test"
Requires-Dist: pytest-cov>=2.10.0; extra == "test"
Requires-Dist: pytest-rerunfailures>=9.1.1; extra == "test"
Provides-Extra: test-petab
Requires-Dist: petabtests>=0.0.0a6; extra == "test-petab"
Dynamic: download-url
Dynamic: license-file
